docker_services_cli/__init__.py
docker_services_cli/cli.py
docker_services_cli/config.py
docker_services_cli/docker-services.yml
docker_services_cli/env.py
docker_services_cli/services.py
Docker_Services_CLI-0.12.1.dist-info/AUTHORS.rst
Docker_Services_CLI-0.12.1.dist-info/LICENSE
Docker_Services_CLI-0.12.1.dist-info/METADATA
Docker_Services_CLI-0.12.1.dist-info/WHEEL
Docker_Services_CLI-0.12.1.dist-info/entry_points.txt
Docker_Services_CLI-0.12.1.dist-info/top_level.txt
Docker_Services_CLI-0.12.1.dist-info/RECORD
