Metadata-Version: 2.1
Name: Docker-Services-CLI
Version: 0.12.1
Summary: Python module to ease the creation and management of external services.
Home-page: https://github.com/inveniosoftware/docker-services-cli
Author: CERN
Author-email: info@inveniosoftware.org
License: MIT
Keywords: docker services cli
Platform: any
Classifier: Development Status :: 3 - Alpha
Requires-Python: >=3.8
License-File: LICENSE
License-File: AUTHORS.rst
Requires-Dist: click>=7.0
Provides-Extra: tests
Requires-Dist: check-manifest>=0.42; extra == "tests"
Requires-Dist: pytest-black-ng>=0.4.0; extra == "tests"
Requires-Dist: pytest-cov>=3.0.0; extra == "tests"
Requires-Dist: pytest-isort>=3.0.0; extra == "tests"
Requires-Dist: pytest-pydocstyle>=2.2.3; extra == "tests"
Requires-Dist: pytest-pycodestyle>=2.2.0; extra == "tests"
Requires-Dist: pytest<7.2.0,>=6; extra == "tests"
Requires-Dist: sphinx>=4.5; extra == "tests"
